pytest_func_cov/__init__.py
pytest_func_cov/plugin.py
pytest_func_cov/tracking.py
pytest_func_cov-0.2.3.dist-info/LICENSE
pytest_func_cov-0.2.3.dist-info/METADATA
pytest_func_cov-0.2.3.dist-info/WHEEL
pytest_func_cov-0.2.3.dist-info/entry_points.txt
pytest_func_cov-0.2.3.dist-info/top_level.txt
pytest_func_cov-0.2.3.dist-info/RECORD
