Metadata-Version: 2.1
Name: pytest-func-cov
Version: 0.2.3
Summary: Pytest plugin for measuring function coverage
Home-page: https://github.com/radug0314/pytest_func_cov
Author: Radu Ghitescu
Author-email: radu.ghitescu@gmail.com
License: MIT
Platform: UNKNOWN
Classifier: Framework :: Pytest
Classifier: Development Status :: 3 - Alpha
Classifier: Intended Audience :: Developers
Requires-Python: >=3.6
